MANIFEST.in
setup.cfg
setup.py
kotti_video/__init__.py
kotti_video/__init__.pyc
kotti_video/resources.py
kotti_video/resources.pyc
kotti_video/views.py
kotti_video/views.pyc
kotti_video.egg-info/PKG-INFO
kotti_video.egg-info/SOURCES.txt
kotti_video.egg-info/dependency_links.txt
kotti_video.egg-info/not-zip-safe
kotti_video.egg-info/requires.txt
kotti_video.egg-info/top_level.txt
kotti_video/static/background.png
kotti_video/static/bigplay.png
kotti_video/static/controls-ted.png
kotti_video/static/controls-wmp-bg.png
kotti_video/static/controls-wmp.png
kotti_video/static/controls.png
kotti_video/static/flashmediaelement.swf
kotti_video/static/jquery.js
kotti_video/static/loading.gif
kotti_video/static/mediaelement-and-player.js
kotti_video/static/mediaelement-and-player.min.js
kotti_video/static/mediaelement.js
kotti_video/static/mediaelement.min.js
kotti_video/static/mediaelementplayer.css
kotti_video/static/mediaelementplayer.js
kotti_video/static/mediaelementplayer.min.css
kotti_video/static/mediaelementplayer.min.js
kotti_video/static/mejs-skins.css
kotti_video/static/silverlightmediaelement.xap
kotti_video/templates/video-view.pt